pydarnio/__init__.py
pydarnio/dmap_wrapper.py
pydarnio/borealis/__init__.py
pydarnio/borealis/base_format.py
pydarnio/borealis/borealis.py
pydarnio/borealis/borealis_array.py
pydarnio/borealis/borealis_convert.py
pydarnio/borealis/borealis_formats.py
pydarnio/borealis/borealis_restructure.py
pydarnio/borealis/borealis_site.py
pydarnio/borealis/borealis_utilities.py
pydarnio/borealis/v1_onwards.py
pydarnio/exceptions/__init__.py
pydarnio/exceptions/borealis_exceptions.py
pydarnio/exceptions/warning_formatting.py
pydarnio/utils/__init__.py
pydarnio/utils/conversions.py
pydarnio-2.0.dist-info/licenses/LICENSE
pydarnio-2.0.dist-info/METADATA
pydarnio-2.0.dist-info/WHEEL
pydarnio-2.0.dist-info/top_level.txt
pydarnio-2.0.dist-info/RECORD
