Metadata-Version: 2.4
Name: pydarnio
Version: 2.0
Summary: Python library for reading and writing SuperDARN data
Home-page: https://pydarnio.readthedocs.io/en/latest/
Author: SuperDARN
Classifier: Development Status :: 5 - Production/Stable
Classifier: License :: OSI Approved :: GNU Lesser General Public License v3 (LGPLv3)
Classifier: Programming Language :: Python :: 3.8
Requires-Python: >=3.8
License-File: LICENSE
Requires-Dist: numpy<3
Requires-Dist: h5py>=3.11.0
Requires-Dist: darn-dmap==0.4.0
Provides-Extra: xarray
Requires-Dist: h5netcdf; extra == "xarray"
Requires-Dist: xarray; extra == "xarray"
Dynamic: license-file
